birgitta/__init__.py
birgitta/context/__init__.py
birgitta/dataframe/__init__.py
birgitta/dataframe/dataframe.py
birgitta/dataframe/dfdiff.py
birgitta/dataframe/storage.py
birgitta/dataframesource/__init__.py
birgitta/dataframesource/contextsource.py
birgitta/dataframesource/dataframesourcebase.py
birgitta/dataframesource/sources/__init__.py
birgitta/dataframesource/sources/dataikusource.py
birgitta/dataframesource/sources/localsource.py
birgitta/dataframesource/sources/s3source.py
birgitta/dataiku/__init__.py
birgitta/dataiku/dataset/__init__.py
birgitta/dataiku/dataset/manage/__init__.py
birgitta/dataiku/dataset/manage/schema.py
birgitta/dataiku/libtest/__init__.py
birgitta/dataiku/libtest/libtest.py
birgitta/dataiku/platform/__init__.py
birgitta/dataiku/recipe/__init__.py
birgitta/dataiku/recipe/manage.py
birgitta/dataiku/recipetest/__init__.py
birgitta/dataiku/recipetest/scenariotest.py
birgitta/dataiku/recipetest/examples/__init__.py
birgitta/dataiku/recipetest/examples/simplescenario.py
birgitta/dataiku/schema/__init__.py
birgitta/dataset/__init__.py
birgitta/dataset/dataset.py
birgitta/fields/__init__.py
birgitta/fields/catalog.py
birgitta/notebook/__init__.py
birgitta/project/__init__.py
birgitta/project/find.py
birgitta/project/project.py
birgitta/recipe/__init__.py
birgitta/recipe/diff.py
birgitta/recipe/find.py
birgitta/recipe/params.py
birgitta/recipe/runner.py
birgitta/recipe/debug/__init__.py
birgitta/recipe/debug/dataframe.py
birgitta/recipetest/__init__.py
birgitta/recipetest/validate.py
birgitta/recipetest/coverage/__init__.py
birgitta/recipetest/coverage/report.py
birgitta/recipetest/coverage/transform.py
birgitta/recipetest/examples/__init__.py
birgitta/recipetest/localtest/__init__.py
birgitta/recipetest/localtest/assertion.py
birgitta/recipetest/localtest/conftest.py
birgitta/recipetest/localtest/fixturing.py
birgitta/recipetest/localtest/script_prepend.py
birgitta/schema/__init__.py
birgitta/schema/nullable.py
birgitta/schema/schema.py
birgitta-0.1.37.dist-info/LICENSE
birgitta-0.1.37.dist-info/METADATA
birgitta-0.1.37.dist-info/WHEEL
birgitta-0.1.37.dist-info/entry_points.txt
birgitta-0.1.37.dist-info/top_level.txt
birgitta-0.1.37.dist-info/RECORD
