Metadata-Version: 2.1
Name: birgitta
Version: 0.1.37
Summary: Pyspark and notebook unit testing, especially focused on Dataiku.
Home-page: https://github.com/telia-oss/birgitta
Author: Telia Norge
Author-email: UNKNOWN
License: MIT
Platform: UNKNOWN
Classifier: Development Status :: 3 - Alpha
Classifier: License :: OSI Approved :: MIT License
Classifier: Intended Audience :: Developers
Classifier: Natural Language :: English
Classifier: Operating System :: OS Independent
Classifier: Programming Language :: Python
Requires-Dist: docopt
Requires-Dist: numpy
Requires-Dist: pyspark
Requires-Dist: mock
Requires-Dist: pandas
Requires-Dist: pyarrow
Requires-Dist: pytest
Requires-Dist: pytest-cov
Requires-Dist: pytest-mock
Requires-Dist: holidays
